setup_pybrv_etlmeta/__init__.py
setup_pybrv_etlmeta/pybrv_etlmeta.py
setup_pybrv_etlmeta-0.1.6.dist-info/LICENSE
setup_pybrv_etlmeta-0.1.6.dist-info/METADATA
setup_pybrv_etlmeta-0.1.6.dist-info/WHEEL
setup_pybrv_etlmeta-0.1.6.dist-info/entry_points.txt
setup_pybrv_etlmeta-0.1.6.dist-info/top_level.txt
setup_pybrv_etlmeta-0.1.6.dist-info/RECORD
