Metadata-Version: 2.2
Name: setup_pybrv_etlmeta
Version: 0.1.6
Summary: A Databricks-compatible package to create etl_meta schema and rule validation tables
Home-page: https://github.com/Ashu28555/setup_pybrv_etlmeta
Author: Ashutosh Semwal
Author-email: info@complereinfosystem.com
Classifier: Programming Language :: Python :: 3
Classifier: Operating System :: OS Independent
License-File: LICENSE
Dynamic: author
Dynamic: author-email
Dynamic: classifier
Dynamic: description
Dynamic: description-content-type
Dynamic: home-page
Dynamic: summary
